LICENSE
README.md
torch_kindling/norm/__init__.py
torch_kindling/norm/rin.py
torch_kindling-0.0.0.dist-info/METADATA
torch_kindling-0.0.0.dist-info/WHEEL
torch_kindling-0.0.0.dist-info/licenses/LICENSE
torch_kindling-0.0.0.dist-info/RECORD
