Metadata-Version: 2.4
Name: torch-kindling
Version: 0.0.0
Summary: A simple torch layer library for research replication.
Project-URL: Homepage, https://github.com/alexcolpitts96/torch-kindling
Project-URL: Issues, https://github.com/alexcolpitts96/torch-kindling/issues
Author-email: Alex Colpitts <alex.colpitts@gmail.com>
License: MIT License
License-File: LICENSE
Requires-Python: >=3.10
Requires-Dist: torch>=2.0.0
Provides-Extra: dev
Requires-Dist: black>=23.0; extra == 'dev'
Requires-Dist: flake8>=6.0; extra == 'dev'
Requires-Dist: isort>=5.12; extra == 'dev'
Requires-Dist: mypy>=1.0; extra == 'dev'
Requires-Dist: pre-commit; extra == 'dev'
Requires-Dist: pytest>=7.0; extra == 'dev'
